{"0": {"obs80": "     ADADFDA  C2023 11 15.31751 08 16 51.83 -24 29 31.7          18.3 V      807", "name": "     ADADFDA ", "year": "2023", "month": "11", "day": "15", "time": "0.31751", "ra_hour": "08", "ra_minutes": "16", "ra_seconds": "51.83", "ra_hms": "08:16:51.83", "dec_degrees": "-24", "dec_minutes": "29", "dec_seconds": "31.7", "dec_dms": "-24:29:31.7", "mag": "18.27", "filter": "V", "obs_code": "807", "phot_snr": " 3.78", "ra_error_arc_minutes": "0.22", "dec_error_arc_minutes": "0.22", "mag_error": "0.33", "x_pixel": " 579.89", "y_pixel": " 367.38", "flux": "    226", "fwhm": " 0.8", "snr": "   1.7 ", "fit_rms": "0.453", "usesnr": 3.78, "pos_unc": 0.21}, "1": {"obs80": "     ASDFDD   C2023 11 15.31751 08 16 58.78 -24 27 45.0          18.2 V      807", "name": "     ASDFDD  ", "year": "2023", "month": "11", "day": "15", "time": "0.31751", "ra_hour": "08", "ra_minutes": "16", "ra_seconds": "58.78", "ra_hms": "08:16:58.78", "dec_degrees": "-24", "dec_minutes": "27", "dec_seconds": "45.0", "dec_dms": "-24:27:45.0", "mag": "18.24", "filter": "V", "obs_code": "807", "phot_snr": " 3.78", "ra_error_arc_minutes": "0.12", "dec_error_arc_minutes": "0.12", "mag_error": "0.26", "x_pixel": " 507.00", "y_pixel": " 296.00", "flux": "    233", "fwhm": " 0.5", "snr": "   2.5 ", "fit_rms": "0.431", "usesnr": 3.78, "pos_unc": 0.13}, "2": {"obs80": "     K23V08C KC2023 11 15.34105 05 36 34.28 -18 00 07.4          20.2 V      807", "name": "     K23V08C ", "year": "2023", "month": "11", "day": "15", "time": "0.34105", "ra_hour": "05", "ra_minutes": "36", "ra_seconds": "34.28", "ra_hms": "05:36:34.28", "dec_degrees": "-18", "dec_minutes": "00", "dec_seconds": "07.4", "dec_dms": "-18:00:07.4", "mag": "20.18", "filter": "V", "obs_code": "807", "phot_snr": " 5.95", "ra_error_arc_minutes": "0.33", "dec_error_arc_minutes": "0.33", "mag_error": "0.17", "x_pixel": " 513.79", "y_pixel": " 497.69", "flux": "     71", "fwhm": " 3.3", "snr": "   4.4 ", "fit_rms": "0.214", "usesnr": 5.95, "pos_unc": 0.55}, "3": {"obs80": "     K23V08C KC2023 11 15.34473 05 36 34.26 -17 59 51.1          20.0 V      807", "name": "     K23V08C ", "year": "2023", "month": "11", "day": "15", "time": "0.34473", "ra_hour": "05", "ra_minutes": "36", "ra_seconds": "34.26", "ra_hms": "05:36:34.26", "dec_degrees": "-17", "dec_minutes": "59", "dec_seconds": "51.1", "dec_dms": "-17:59:51.1", "mag": "20.01", "filter": "V", "obs_code": "807", "phot_snr": " 7.27", "ra_error_arc_minutes": "0.30", "dec_error_arc_minutes": "0.30", "mag_error": "0.14", "x_pixel": " 514.66", "y_pixel": " 509.31", "flux": "     75", "fwhm": " 3.4", "snr": "   4.9 ", "fit_rms": "0.161", "usesnr": 7.27, "pos_unc": 0.47}, "4": {"obs80": "     K23V08C KC2023 11 15.34849 05 36 34.28 -17 59 33.8          20.3 V      807", "name": "     K23V08C ", "year": "2023", "month": "11", "day": "15", "time": "0.34849", "ra_hour": "05", "ra_minutes": "36", "ra_seconds": "34.28", "ra_hms": "05:36:34.28", "dec_degrees": "-17", "dec_minutes": "59", "dec_seconds": "33.8", "dec_dms": "-17:59:33.8", "mag": "20.35", "filter": "V", "obs_code": "807", "phot_snr": " 5.32", "ra_error_arc_minutes": "0.31", "dec_error_arc_minutes": "0.31", "mag_error": "0.19", "x_pixel": " 515.76", "y_pixel": " 521.38", "flux": "     53", "fwhm": " 1.9", "snr": "   2.7 ", "fit_rms": "0.421", "usesnr": 5.32, "pos_unc": 0.36}, "5": {"obs80": "     K23V08C KC2023 11 15.35217 05 36 34.23 -17 59 16.5          19.4 V      807", "name": "     K23V08C ", "year": "2023", "month": "11", "day": "15", "time": "0.35217", "ra_hour": "05", "ra_minutes": "36", "ra_seconds": "34.23", "ra_hms": "05:36:34.23", "dec_degrees": "-17", "dec_minutes": "59", "dec_seconds": "16.5", "dec_dms": "-17:59:16.5", "mag": "19.43", "filter": "V", "obs_code": "807", "phot_snr": " 9.18", "ra_error_arc_minutes": "0.21", "dec_error_arc_minutes": "0.21", "mag_error": "0.11", "x_pixel": " 515.38", "y_pixel": " 533.92", "flux": "    104", "fwhm": " 3.2", "snr": "   6.7 ", "fit_rms": "0.104", "usesnr": 9.18, "pos_unc": 0.35}}