<?xml version="1.0" ?>
<ades version="2022">
	<obsBlock>
		<obsContext>
			<observatory>
				<mpcCode>807</mpcCode>
				<name>Cerro Tololo Inter-American Observatory</name>
			</observatory>
			<submitter>
				<name>R. Holmes</name>
			</submitter>
			<observers>
				<name>T. Linder, R. Holmes</name>
			</observers>
			<measurers>
				<name>T. Linder, R. Holmes</name>
			</measurers>
			<telescope>
				<design>Ritchey-Chretien</design>
				<aperture>0.61</aperture>
				<detector>CCD</detector>
				<fRatio>11</fRatio>
			</telescope>
			<fundingSource>NASA</fundingSource>
		</obsContext>
		<obsData>
			<optical>
				<provID>2023 VJ6</provID>
				<trkSub>K23V06J</trkSub>
				<mode>CCD</mode>
				<stn>807</stn>
				<obsTime>2024-01-05T02:58:04.22Z</obsTime>
				<ra>66.257292</ra>
				<dec>-15.298167</dec>
				<rmsRA>0.41</rmsRA>
				<rmsDec>0.41</rmsDec>
				<astCat>Gaia2</astCat>
				<mag>21.8</mag>
				<rmsMag>0.13</rmsMag>
				<band>G</band>
			</optical>
			<optical>
				<provID>2023 VJ6</provID>
				<trkSub>K23V06J</trkSub>
				<mode>CCD</mode>
				<stn>807</stn>
				<obsTime>2024-01-05T03:06:40.90Z</obsTime>
				<ra>66.259667</ra>
				<dec>-15.301194</dec>
				<rmsRA>0.49</rmsRA>
				<rmsDec>0.49</rmsDec>
				<astCat>Gaia2</astCat>
				<mag>21.6</mag>
				<rmsMag>0.15</rmsMag>
				<band>G</band>
			</optical>
			<optical>
				<provID>2023 VJ6</provID>
				<trkSub>K23V06J</trkSub>
				<mode>CCD</mode>
				<stn>807</stn>
				<obsTime>2024-01-05T03:15:17.56Z</obsTime>
				<ra>66.262</ra>
				<dec>-15.304306</dec>
				<rmsRA>0.48</rmsRA>
				<rmsDec>0.48</rmsDec>
				<astCat>Gaia2</astCat>
				<mag>21.7</mag>
				<rmsMag>0.10</rmsMag>
				<band>G</band>
			</optical>
		</obsData>
	</obsBlock>
</ades>
