<?xml version="1.0" ?>
<ades version="2022">
	<obsBlock>
		<obsContext>
			<observatory>
				<mpcCode>807</mpcCode>
				<name>Cerro Tololo Inter-American Observatory</name>
			</observatory>
			<submitter>
				<name>R. Holmes</name>
			</submitter>
			<observers>
				<name>T. Linder, R. Holmes, L. Horn</name>
			</observers>
			<measurers>
				<name>T. Linder, R. Holmes, L. Horn</name>
			</measurers>
			<telescope>
				<design>Ritchey-Chretien</design>
				<aperture>0.61</aperture>
				<detector>CCD</detector>
				<fRatio>11</fRatio>
			</telescope>
			<fundingSource>NASA</fundingSource>
		</obsContext>
		<obsData>
			<optical>
				<provID>2023 XA10</provID>
				<trkSub>K23X10A</trkSub>
				<mode>CCD</mode>
				<stn>807</stn>
				<obsTime>2024-01-01T04:02:28.90Z</obsTime>
				<ra>66.195708</ra>
				<dec>-36.32125</dec>
				<rmsRA>0.39</rmsRA>
				<rmsDec>0.39</rmsDec>
				<astCat>Gaia2</astCat>
				<mag>21.4</mag>
				<rmsMag>0.15</rmsMag>
				<band>G</band>
			</optical>
			<optical>
				<provID>2023 XA10</provID>
				<trkSub>K23X10A</trkSub>
				<mode>CCD</mode>
				<stn>807</stn>
				<obsTime>2024-01-01T04:11:05.56Z</obsTime>
				<ra>66.208792</ra>
				<dec>-36.328306</dec>
				<rmsRA>0.68</rmsRA>
				<rmsDec>0.68</rmsDec>
				<astCat>Gaia2</astCat>
				<mag>21.4 </mag>
				<rmsMag>0.14</rmsMag>
				<band>G</band>
			</optical>
			<optical>
				<provID>2023 XA10</provID>
				<trkSub>K23X10A</trkSub>
				<mode>CCD</mode>
				<stn>807</stn>
				<obsTime>2024-01-01T04:19:42.24Z</obsTime>
				<ra>66.222167</ra>
				<dec>-36.335056</dec>
				<rmsRA>0.43</rmsRA>
				<rmsDec>0.43</rmsDec>
				<astCat>Gaia2</astCat>
				<mag>21.2 </mag>
				<rmsMag>0.09</rmsMag>
				<band>G</band>
			</optical>
		</obsData>
	</obsBlock>
</ades>
